{"users":[{"usr":"admin","pwd":"123"}],"contacts":[{"id":"cnt0","name":"w","lastname":"sdfsdf","phone":"000111","mobile":"","email":"","address":"","birthday":""},{"id":"cnt1","name":"w2","lastname":"aaaa","phone":"234234","mobile":"","email":"","address":"","birthday":""},{"id":"cnt2","name":"w","lastname":"a","phone":"4","mobile":"","email":"","address":"","birthday":""},{"id":"cnt3","name":"w","lastname":"a","phone":"4","mobile":"","email":"","address":"","birthday":""},{"id":"cnt4","name":"w","lastname":"a","phone":"4","mobile":"","email":"","address":"","birthday":""},{"id":"cnt5","name":"w","lastname":"a","phone":"4","mobile":"","email":"","address":"","birthday":""}]}